platzky_redirections/__init__.py
platzky_redirections/entrypoint.py
platzky_redirections-0.1.0.dist-info/METADATA
platzky_redirections-0.1.0.dist-info/WHEEL
platzky_redirections-0.1.0.dist-info/RECORD
